flake8_type_annotations.py
flake8_type_annotations-0.1.0.dist-info/entry_points.txt
flake8_type_annotations-0.1.0.dist-info/LICENSE
flake8_type_annotations-0.1.0.dist-info/WHEEL
flake8_type_annotations-0.1.0.dist-info/METADATA
flake8_type_annotations-0.1.0.dist-info/RECORD
